vecstream/__init__.py
vecstream/binary_store.py
vecstream/cli.py
vecstream/client.py
vecstream/collections.py
vecstream/hnsw_index.py
vecstream/index_manager.py
vecstream/persistent_store.py
vecstream/query_engine.py
vecstream/server.py
vecstream/vector_store.py
vecstream-0.3.4.dist-info/licenses/LICENSE
vecstream-0.3.4.dist-info/METADATA
vecstream-0.3.4.dist-info/WHEEL
vecstream-0.3.4.dist-info/entry_points.txt
vecstream-0.3.4.dist-info/top_level.txt
vecstream-0.3.4.dist-info/RECORD
